hallo/__init__.py
hallo/__main__.py
hallo/command.py
hallo/install.sh
hallo/frame/__init__.py
hallo/frame/config.py
hallo/frame/console.py
hallo/frame/main.py
hallo/frame/requirements.txt
hallo/frame/app/__init__.py
hallo/frame/app/base.py
hallo/frame/app/router.py
hallo/frame/app/console/__init__.py
hallo/frame/app/console/base.py
hallo/frame/app/console/secret.py
hallo/frame/app/console/table.py
hallo/frame/app/helper/__init__.py
hallo/frame/app/helper/console.py
hallo/frame/app/helper/decorator.py
hallo/frame/app/helper/file.py
hallo/frame/app/helper/functions.py
hallo/frame/app/helper/oss.py
hallo/frame/app/helper/router.py
hallo/frame/app/models/__init__.py
hallo/frame/app/models/user.py
hallo/frame/app/module/__init__.py
hallo/frame/app/module/base.py
hallo/frame/app/module/file.py
hallo/frame/app/module/index.py
hallo/frame/app/module/oss.py
hallo/frame/app/module/session/__init__.py
hallo/frame/app/module/session/user.py
hallo/frame/app/module/token/__init__.py
hallo/frame/app/module/token/user.py
hallo/frame/sql/user.sql
hallo/frame/static/favicon.ico
hallo/frame/static/css/index.css
hallo/frame/static/images/index.png
hallo/frame/static/js/index.js
hallo/frame/templates/index/index.html
Hallo-1.0.2.dist-info/LICENSE
Hallo-1.0.2.dist-info/METADATA
Hallo-1.0.2.dist-info/WHEEL
Hallo-1.0.2.dist-info/entry_points.txt
Hallo-1.0.2.dist-info/top_level.txt
Hallo-1.0.2.dist-info/RECORD
