Metadata-Version: 2.1
Name: Hallo
Version: 1.0.2
Summary: web mvc framework for python
Home-page: https://github.com/oldjun/hallo
Author: JP Chen
Author-email: oldjun@sina.com
License: MIT
Platform: UNKNOWN
Classifier: Programming Language :: Python :: 3.6
Classifier: Intended Audience :: Developers
Classifier: License :: OSI Approved :: MIT License
Classifier: Topic :: Internet :: WWW/HTTP :: WSGI :: Application
Requires-Python: >=3.6
License-File: LICENSE
